{
  "active_process": "HWND(132572)",
  "active_window_title": "cd \"C:\\Users\\chiki\\OneDrive\\Desktop\\GitHib Repo\\rowdyhack-25\\client\\eyecore_mvp\"; $env:ACCESS_CODE = \"96HGLS1I7F\"; $env:RUST_LOG = \"info\"; .\\target\\release\\eyecore_mvp.exe",
  "cpu_usage": 92.02249908447266,
  "focus_level": 0.07999999821186066,
  "memory_usage": 89.88539123535156,
  "recording_started_at": "2025-10-26T09:56:47.367172500+00:00",
  "session_id": "8d68ea1a-af1e-41dd-b8a1-7c3df27b3796",
  "timestamp": "2025-10-26T09:56:47.302751500+00:00",
  "voice_enabled": true
}