{
  "id": "311d123d-f192-46d3-8a09-c96d743ba9b2",
  "timestamp": "2025-10-25T21:51:19.871307200Z",
  "session_id": "0e4025d6-a878-4b41-a6d5-6f94a1cd16a8",
  "flag_type": {
    "type": "ProductivityAlert"
  },
  "severity": "Medium",
  "title": "Low Focus Level",
  "description": "Focus level at 0.21 is below threshold of 0.30",
  "data_source": "focus_metrics",
  "metrics": {
    "context_switches": 0,
    "focus_level": 0.20999999344348907,
    "threshold": 0.30000001192092896
  },
  "confidence": 0.8
}